vispunk_motion
